<?xml version="1.0" encoding="UTF-8"?><account><account><email>khello@yo.com</email><enabled>false</enabled><id>0</id><password>gello</password><username>hello</username></account><account><email>khello@yo.com</email><enabled>false</enabled><id>0</id><password>gello</password><username>hello</username></account><account><email>khello@yo.com</email><enabled>false</enabled><id>0</id><password>gello</password><username>hello</username></account><account><email>khello@yo.com</email><enabled>false</enabled><id>0</id><password>gello</password><username>hello</username></account><account><email>khello@yo.com</email><enabled>false</enabled><id>0</id><password>gello</password><username>hello</username></account><account><email>khello@yo.com</email><enabled>false</enabled><id>0</id><password>gello</password><username>hello</username></account><account><email>khello@yo.com</email><enabled>false</enabled><id>0</id><password>gello</password><username>hello</username></account><account><email>khello@yo.com</email><enabled>false</enabled><id>0</id><password>gello</password><username>hello</username></account><account><email>khello@yo.com</email><enabled>false</enabled><id>0</id><password>gello</password><username>hello</username></account><account><email>khello@yo.com</email><enabled>false</enabled><id>0</id><password>gello</password><username>hello</username></account><account><email>khello@yo.com</email><enabled>false</enabled><id>0</id><password>gello</password><username>hello</username></account><account><email>khello@yo.com</email><enabled>false</enabled><id>0</id><password>gello</password><username>hello</username></account><account><email>khello@yo.com</email><enabled>false</enabled><id>0</id><password>gello</password><username>hello</username></account><account><email>khello@yo.com</email><enabled>false</enabled><id>0</id><password>gello</password><username>hello</username></account><account><email>khello@yo.com</email><enabled>false</enabled><id>0</id><password>gello</password><username>hello</username></account><account><email>khello@yo.com</email><enabled>false</enabled><id>0</id><password>gello</password><username>hello</username></account><account><email>khello@yo.com</email><enabled>false</enabled><id>0</id><password>gello</password><username>hello</username></account><account><email>khello@yo.com</email><enabled>false</enabled><id>0</id><password>gello</password><username>hello</username></account><account><email>khello@yo.com</email><enabled>false</enabled><id>0</id><password>gello</password><username>hello</username></account><account><email>khello@yo.com</email><enabled>false</enabled><id>0</id><password>gello</password><username>hello</username></account><account><email>khello@yo.com</email><enabled>false</enabled><id>0</id><password>gello</password><username>hello</username></account><account><email>khello@yo.com</email><enabled>false</enabled><id>0</id><password>gello</password><username>hello</username></account><account><email>khello@yo.com</email><enabled>false</enabled><id>0</id><password>gello</password><username>hello</username></account><account><email>khello@yo.com</email><enabled>false</enabled><id>0</id><password>gello</password><username>hello</username></account></account>